CHANGES.txt
MANIFEST.in
README.txt
setup.py
docs/INSTALL.txt
docs/LICENSE.GPL
docs/LICENSE.txt
docs/TODO.txt
p4a/__init__.py
p4a/__init__.pyc
p4a.subtyper.egg-info/PKG-INFO
p4a.subtyper.egg-info/SOURCES.txt
p4a.subtyper.egg-info/dependency_links.txt
p4a.subtyper.egg-info/entry_points.txt
p4a.subtyper.egg-info/namespace_packages.txt
p4a.subtyper.egg-info/not-zip-safe
p4a.subtyper.egg-info/requires.txt
p4a.subtyper.egg-info/top_level.txt
p4a/subtyper/__init__.py
p4a/subtyper/browser.py
p4a/subtyper/browser.txt
p4a/subtyper/configure.zcml
p4a/subtyper/default.py
p4a/subtyper/engine.py
p4a/subtyper/interfaces.py
p4a/subtyper/menu.py
p4a/subtyper/meta.zcml
p4a/subtyper/rebuild_i18n.sh
p4a/subtyper/sitesetup.py
p4a/subtyper/submenu.py
p4a/subtyper/subtyping.txt
p4a/subtyper/tests.py
p4a/subtyper/utils.py
p4a/subtyper/Extensions/Install.py
p4a/subtyper/Extensions/__init__.py
p4a/subtyper/contentmenu/README.txt
p4a/subtyper/contentmenu/__init__.py
p4a/subtyper/contentmenu/browser.py
p4a/subtyper/contentmenu/browser.txt
p4a/subtyper/contentmenu/configure.zcml
p4a/subtyper/contentmenu/global_contentmenu.pt
p4a/subtyper/contentmenu/meta.zcml
p4a/subtyper/contentmenu/tests.py
p4a/subtyper/locales/p4a.subtyper-manual.pot
p4a/subtyper/locales/p4a.subtyper.pot
p4a/subtyper/locales/es/LC_MESSAGES/p4a.subtyper.po
p4a/subtyper/locales/eu/LC_MESSAGES/p4a.subtyper.po
p4a/subtyper/profiles/default/componentregistry.xml
p4a/subtyper/profiles/default/metadata.xml
p4a/subtyper/skins/p4a_subtyper/global_contentviews.pt