Metadata-Version: 1.1
Name: p4a.subtyper
Version: 2.0
Summary: Subtyping framework for Plone
Home-page: https://svn.plone.org/svn/collective/p4a/p4a.subtyper/
Author: Rocky Burt
Author-email: rocky@serverzen.com
License: GPL
Platform: UNKNOWN
Classifier: Framework :: Zope2
Classifier: Framework :: Zope3
Classifier: Programming Language :: Python
Classifier: Topic :: Software Development :: Libraries :: Python Modules
